.coveragerc
.isort.cfg
CHANGES.rst
MANIFEST.in
Makefile
README.rst
buildout.cfg
ci.cfg
requirements.txt
setup.py
docs/LICENSE.GPL
docs/LICENSE.rst
src/imio/__init__.py
src/imio.dashboard.egg-info/PKG-INFO
src/imio.dashboard.egg-info/SOURCES.txt
src/imio.dashboard.egg-info/dependency_links.txt
src/imio.dashboard.egg-info/entry_points.txt
src/imio.dashboard.egg-info/namespace_packages.txt
src/imio.dashboard.egg-info/not-zip-safe
src/imio.dashboard.egg-info/requires.txt
src/imio.dashboard.egg-info/top_level.txt
src/imio/dashboard/__init__.py
src/imio/dashboard/adapters.py
src/imio/dashboard/columns.py
src/imio/dashboard/columns.zcml
src/imio/dashboard/config.py
src/imio/dashboard/configure.zcml
src/imio/dashboard/interfaces.py
src/imio/dashboard/mk_sync_locales.sh
src/imio/dashboard/monkey.py
src/imio/dashboard/overrides.zcml
src/imio/dashboard/setuphandlers.py
src/imio/dashboard/testing.py
src/imio/dashboard/testing.zcml
src/imio/dashboard/upgrades.zcml
src/imio/dashboard/vocabulary.py
src/imio/dashboard/browser/__init__.py
src/imio/dashboard/browser/configure.zcml
src/imio/dashboard/browser/facetedcollectionportlet.py
src/imio/dashboard/browser/overrides.py
src/imio/dashboard/browser/static/.gitkeep
src/imio/dashboard/browser/static/imio.dashboard.js
src/imio/dashboard/browser/templates/category_contact.pt
src/imio/dashboard/browser/templates/default_widgets.xml
src/imio/dashboard/browser/templates/generationlinks.pt
src/imio/dashboard/browser/templates/portlet_facetedcollection.pt
src/imio/dashboard/browser/templates/term.pt
src/imio/dashboard/browser/templates/two_tables.pt
src/imio/dashboard/browser/templates/widget.pt
src/imio/dashboard/content/__init__.py
src/imio/dashboard/content/configure.zcml
src/imio/dashboard/content/dashboardcollection.py
src/imio/dashboard/content/pod_template.py
src/imio/dashboard/faceted_conf/contact-lists-searches.xml
src/imio/dashboard/faceted_conf/held-positions-searches.xml
src/imio/dashboard/faceted_conf/organizations-searches.xml
src/imio/dashboard/faceted_conf/persons-searches.xml
src/imio/dashboard/locales/collective.eeafaceted.z3ctable.pot
src/imio/dashboard/locales/eea.pot
src/imio/dashboard/locales/imio.dashboard.pot
src/imio/dashboard/locales/manual.pot
src/imio/dashboard/locales/en/LC_MESSAGES/collective.eeafaceted.z3ctable.po
