Metadata-Version: 2.1
Name: imio.dashboard
Version: 2.12
Summary: This package adds functionnality to collective.eeafaceted.dashboard but only work for Plone 4.3.x
Home-page: http://pypi.python.org/pypi/imio.dashboard
Author: IMIO
Author-email: dev@imio.be
License: GPL V2
Keywords: Python Zope Plone
Platform: UNKNOWN
Classifier: Development Status :: 6 - Mature
Classifier: Environment :: Web Environment
Classifier: Framework :: Plone
Classifier: Framework :: Plone :: 4.3
Classifier: Programming Language :: Python
Classifier: Programming Language :: Python :: 2.7
Provides-Extra: test
